{
  "@context": "http://iiif.io/api/presentation/2/context.json",
  "@id": "http://example.com/annotations/search/?uri=http%3A%2F%2Fex.co%2Fiiif%2Fcanvas%2F1&manifest=https%3A%2F%2Fgeniza.princeton.edu%2Fen%2Fdocuments%2F15%2Fiiif%2Fmanifest%2F",
  "@type": "sc:AnnotationList",
  "resources": [
    {
      "id": "http://example.com/annotations/42871b73-1c0d-447b-974a-ba812043b360/",
      "type": "Annotation",
      "created": "2022-09-23T15:46:27.924628+00:00",
      "modified": "2022-09-23T15:46:27.924645+00:00",
      "body": [
        {
          "value": "Test annotation"
        }
      ],
      "target": {
        "source": {
          "id": "http://ex.co/iiif/canvas/1",
          "partOf": {
            "id": "https://geniza.princeton.edu/en/documents/15/iiif/manifest/"
          }
        }
      },
      "dc:source": "https://geniza.princeton.edu/sources/16/"
    }
  ]
}